Metadata-Version: 2.1
Name: edx-notices
Version: 0.14.55
Summary: An edx-platform plugin which manages notices that must be acknowledged
Home-page: https://github.com/edx/platform-plugin-notices
Author: edX
Author-email: mtuchfarber@edx.org
License: AGPL 3.0
Keywords: Python edx
Classifier: Development Status :: 3 - Alpha
Classifier: Framework :: Django
Classifier: Framework :: Django :: 3.2
Classifier: Intended Audience :: Developers
Classifier: License :: OSI Approved :: GNU Affero General Public License v3 or later (AGPLv3+)
Classifier: Natural Language :: English
Classifier: Programming Language :: Python :: 3
Classifier: Programming Language :: Python :: 3.8
Requires-Python: >=3.8
License-File: LICENSE.txt
Requires-Dist: Django (>=1.11)
Requires-Dist: django-model-utils
Requires-Dist: django-rest-framework
Requires-Dist: django-simple-history
Requires-Dist: edx-drf-extensions
Requires-Dist: edx-toggles
